e4l/__main__.py
e4l-0.1.4.dist-info/entry_points.txt
e4l-0.1.4.dist-info/LICENSE
e4l-0.1.4.dist-info/WHEEL
e4l-0.1.4.dist-info/METADATA
e4l-0.1.4.dist-info/RECORD
