Metadata-Version: 2.1
Name: e4l
Version: 0.1.4
Summary: enum4linux-ng but pip installable
Home-page: https://github.com/4thel00z/e4l
License: GPL-3
Author: 4thel00z
Author-email: 4thel00z@gmail.com
Requires-Python: >=3.7,<4.0
Classifier: License :: Other/Proprietary License
Classifier: Programming Language :: Python :: 3
Classifier: Programming Language :: Python :: 3.7
Classifier: Programming Language :: Python :: 3.8
Classifier: Programming Language :: Python :: 3.9
Requires-Dist: PyYAML (>=5.4.1,<6.0.0)
Requires-Dist: impacket (>=0.9.23,<0.10.0)
Requires-Dist: ldap3 (>=2.9.1,<3.0.0)
